lstm/__init__.py
lstm/metric/__init__.py
lstm/metric/metric.py
lstm/model/__init__.py
lstm/model/model.py
lstm/model/cnn_bilstm_attention/CBA.py
lstm/model/cnn_bilstm_attention/__init__.py
lstm/util/__init__.py
lstm/util/util.py
lymboy_lstm-1.7.1.dist-info/METADATA
lymboy_lstm-1.7.1.dist-info/WHEEL
lymboy_lstm-1.7.1.dist-info/top_level.txt
lymboy_lstm-1.7.1.dist-info/zip-safe
lymboy_lstm-1.7.1.dist-info/RECORD
