Metadata-Version: 2.1
Name: lymboy-lstm
Version: 1.7.1
Summary: Some out-of-the-box lstm-based time series models
Home-page: https://github.com/lymboy/lymboy-lstm
Author: lymboy.com
Author-email: liusairo@gmail.com
License: MIT
Requires-Dist: scikit-learn
Requires-Dist: plotly
Requires-Dist: keras (~=2.11.0)
Requires-Dist: attention (~=4.1)
